NumpyMijiZhongwenDierBanChuyi/README.md
NumpyMijiZhongwenDierBanChuyi/__init__.py
NumpyMijiZhongwenDierBanChuyi/__main__.py
NumpyMijiZhongwenDierBanChuyi/file.epub
NumpyMijiZhongwenDierBanChuyi/index.html
NumpyMijiZhongwenDierBanChuyi/css/__init__.py
NumpyMijiZhongwenDierBanChuyi/css/annotations.css
NumpyMijiZhongwenDierBanChuyi/css/main.css
NumpyMijiZhongwenDierBanChuyi/css/normalize.css
NumpyMijiZhongwenDierBanChuyi/css/popup.css
NumpyMijiZhongwenDierBanChuyi/font/__init__.py
NumpyMijiZhongwenDierBanChuyi/font/fontello.eot
NumpyMijiZhongwenDierBanChuyi/font/fontello.svg
NumpyMijiZhongwenDierBanChuyi/font/fontello.ttf
NumpyMijiZhongwenDierBanChuyi/font/fontello.woff
NumpyMijiZhongwenDierBanChuyi/img/__init__.py
NumpyMijiZhongwenDierBanChuyi/img/annotator-glyph-sprite.png
NumpyMijiZhongwenDierBanChuyi/img/annotator-icon-sprite.png
NumpyMijiZhongwenDierBanChuyi/img/apple-touch-icon.png
NumpyMijiZhongwenDierBanChuyi/img/cancelfullscreen.png
NumpyMijiZhongwenDierBanChuyi/img/close.png
NumpyMijiZhongwenDierBanChuyi/img/fullscreen.png
NumpyMijiZhongwenDierBanChuyi/img/loader.gif
NumpyMijiZhongwenDierBanChuyi/img/menu-icon.png
NumpyMijiZhongwenDierBanChuyi/img/save.png
NumpyMijiZhongwenDierBanChuyi/img/saved.png
NumpyMijiZhongwenDierBanChuyi/img/settings-s.png
NumpyMijiZhongwenDierBanChuyi/img/settings.png
NumpyMijiZhongwenDierBanChuyi/img/star.png
NumpyMijiZhongwenDierBanChuyi/js/__init__.py
NumpyMijiZhongwenDierBanChuyi/js/epub.js
NumpyMijiZhongwenDierBanChuyi/js/epub.min.js
NumpyMijiZhongwenDierBanChuyi/js/epub.min.map
NumpyMijiZhongwenDierBanChuyi/js/hooks.min.js
NumpyMijiZhongwenDierBanChuyi/js/hooks.min.map
NumpyMijiZhongwenDierBanChuyi/js/reader.js
NumpyMijiZhongwenDierBanChuyi/js/reader.js.map
NumpyMijiZhongwenDierBanChuyi/js/reader.min.js
NumpyMijiZhongwenDierBanChuyi/js/reader.min.map
NumpyMijiZhongwenDierBanChuyi/js/hooks/__init__.py
NumpyMijiZhongwenDierBanChuyi/js/hooks/extensions/__init__.py
NumpyMijiZhongwenDierBanChuyi/js/hooks/extensions/highlight.js
numpy_miji_zhongwen_dier_ban_chuyi-2024.3.5.0.dist-info/METADATA
numpy_miji_zhongwen_dier_ban_chuyi-2024.3.5.0.dist-info/WHEEL
numpy_miji_zhongwen_dier_ban_chuyi-2024.3.5.0.dist-info/entry_points.txt
numpy_miji_zhongwen_dier_ban_chuyi-2024.3.5.0.dist-info/top_level.txt
numpy_miji_zhongwen_dier_ban_chuyi-2024.3.5.0.dist-info/RECORD
